{
  "configVersion": 1,
  "timestamp": 1678042754585,
  "index": "/index.html",
  "assetGroups": [
    {
      "name": "app",
      "installMode": "prefetch",
      "updateMode": "prefetch",
      "cacheQueryOptions": {
        "ignoreVary": true
      },
      "urls": [
        "/favicon.ico",
        "/index.html",
        "/main.29abf87b953e0e6f.js",
        "/manifest.webmanifest",
        "/polyfills.03cfe1edbec1212d.js",
        "/runtime.e7648955bf48ba73.js",
        "/styles.a914d5a691cddd4b.css"
      ],
      "patterns": []
    },
    {
      "name": "assets",
      "installMode": "lazy",
      "updateMode": "prefetch",
      "cacheQueryOptions": {
        "ignoreVary": true
      },
      "urls": [
        "/Derivia-Regular.c8b8089c6db01ce3.otf",
        "/assets/PNG/Default size/Blocks/block_01.png",
        "/assets/PNG/Default size/Blocks/block_02.png",
        "/assets/PNG/Default size/Blocks/block_03.png",
        "/assets/PNG/Default size/Blocks/block_04.png",
        "/assets/PNG/Default size/Blocks/block_05.png",
        "/assets/PNG/Default size/Blocks/block_06.png",
        "/assets/PNG/Default size/Blocks/block_07.png",
        "/assets/PNG/Default size/Blocks/block_08.png",
        "/assets/PNG/Default size/Crates/crate_01.png",
        "/assets/PNG/Default size/Crates/crate_02.png",
        "/assets/PNG/Default size/Crates/crate_03.png",
        "/assets/PNG/Default size/Crates/crate_04.png",
        "/assets/PNG/Default size/Crates/crate_05.png",
        "/assets/PNG/Default size/Crates/crate_06.png",
        "/assets/PNG/Default size/Crates/crate_07.png",
        "/assets/PNG/Default size/Crates/crate_08.png",
        "/assets/PNG/Default size/Crates/crate_09.png",
        "/assets/PNG/Default size/Crates/crate_10.png",
        "/assets/PNG/Default size/Crates/crate_11.png",
        "/assets/PNG/Default size/Crates/crate_12.png",
        "/assets/PNG/Default size/Crates/crate_13.png",
        "/assets/PNG/Default size/Crates/crate_14.png",
        "/assets/PNG/Default size/Crates/crate_15.png",
        "/assets/PNG/Default size/Crates/crate_16.png",
        "/assets/PNG/Default size/Crates/crate_17.png",
        "/assets/PNG/Default size/Crates/crate_18.png",
        "/assets/PNG/Default size/Crates/crate_19.png",
        "/assets/PNG/Default size/Crates/crate_20.png",
        "/assets/PNG/Default size/Crates/crate_21.png",
        "/assets/PNG/Default size/Crates/crate_22.png",
        "/assets/PNG/Default size/Crates/crate_23.png",
        "/assets/PNG/Default size/Crates/crate_24.png",
        "/assets/PNG/Default size/Crates/crate_25.png",
        "/assets/PNG/Default size/Crates/crate_26.png",
        "/assets/PNG/Default size/Crates/crate_27.png",
        "/assets/PNG/Default size/Crates/crate_28.png",
        "/assets/PNG/Default size/Crates/crate_29.png",
        "/assets/PNG/Default size/Crates/crate_30.png",
        "/assets/PNG/Default size/Crates/crate_31.png",
        "/assets/PNG/Default size/Crates/crate_32.png",
        "/assets/PNG/Default size/Crates/crate_33.png",
        "/assets/PNG/Default size/Crates/crate_34.png",
        "/assets/PNG/Default size/Crates/crate_35.png",
        "/assets/PNG/Default size/Crates/crate_36.png",
        "/assets/PNG/Default size/Crates/crate_37.png",
        "/assets/PNG/Default size/Crates/crate_38.png",
        "/assets/PNG/Default size/Crates/crate_39.png",
        "/assets/PNG/Default size/Crates/crate_40.png",
        "/assets/PNG/Default size/Crates/crate_41.png",
        "/assets/PNG/Default size/Crates/crate_42.png",
        "/assets/PNG/Default size/Crates/crate_43.png",
        "/assets/PNG/Default size/Crates/crate_44.png",
        "/assets/PNG/Default size/Crates/crate_45.png",
        "/assets/PNG/Default size/Environment/environment_01.png",
        "/assets/PNG/Default size/Environment/environment_02.png",
        "/assets/PNG/Default size/Environment/environment_03.png",
        "/assets/PNG/Default size/Environment/environment_04.png",
        "/assets/PNG/Default size/Environment/environment_05.png",
        "/assets/PNG/Default size/Environment/environment_06.png",
        "/assets/PNG/Default size/Environment/environment_07.png",
        "/assets/PNG/Default size/Environment/environment_08.png",
        "/assets/PNG/Default size/Environment/environment_09.png",
        "/assets/PNG/Default size/Environment/environment_10.png",
        "/assets/PNG/Default size/Environment/environment_11.png",
        "/assets/PNG/Default size/Environment/environment_12.png",
        "/assets/PNG/Default size/Environment/environment_13.png",
        "/assets/PNG/Default size/Environment/environment_14.png",
        "/assets/PNG/Default size/Environment/environment_15.png",
        "/assets/PNG/Default size/Environment/environment_16.png",
        "/assets/PNG/Default size/Ground/ground_01.png",
        "/assets/PNG/Default size/Ground/ground_02.png",
        "/assets/PNG/Default size/Ground/ground_03.png",
        "/assets/PNG/Default size/Ground/ground_04.png",
        "/assets/PNG/Default size/Ground/ground_05.png",
        "/assets/PNG/Default size/Ground/ground_06.png",
        "/assets/PNG/Default size/Player/player_01.png",
        "/assets/PNG/Default size/Player/player_02.png",
        "/assets/PNG/Default size/Player/player_03.png",
        "/assets/PNG/Default size/Player/player_04.png",
        "/assets/PNG/Default size/Player/player_05.png",
        "/assets/PNG/Default size/Player/player_06.png",
        "/assets/PNG/Default size/Player/player_07.png",
        "/assets/PNG/Default size/Player/player_08.png",
        "/assets/PNG/Default size/Player/player_09.png",
        "/assets/PNG/Default size/Player/player_10.png",
        "/assets/PNG/Default size/Player/player_11.png",
        "/assets/PNG/Default size/Player/player_12.png",
        "/assets/PNG/Default size/Player/player_13.png",
        "/assets/PNG/Default size/Player/player_14.png",
        "/assets/PNG/Default size/Player/player_15.png",
        "/assets/PNG/Default size/Player/player_16.png",
        "/assets/PNG/Default size/Player/player_17.png",
        "/assets/PNG/Default size/Player/player_18.png",
        "/assets/PNG/Default size/Player/player_19.png",
        "/assets/PNG/Default size/Player/player_20.png",
        "/assets/PNG/Default size/Player/player_21.png",
        "/assets/PNG/Default size/Player/player_22.png",
        "/assets/PNG/Default size/Player/player_23.png",
        "/assets/PNG/Default size/Player/player_24.png",
        "/assets/PNG/Default size/playerFace.png",
        "/assets/PNG/Default size/playerFace_dark.png",
        "/assets/PNG/Default size/playerFace_outline.png",
        "/assets/PNG/Retina/Blocks/block_01.png",
        "/assets/PNG/Retina/Blocks/block_02.png",
        "/assets/PNG/Retina/Blocks/block_03.png",
        "/assets/PNG/Retina/Blocks/block_04.png",
        "/assets/PNG/Retina/Blocks/block_05.png",
        "/assets/PNG/Retina/Blocks/block_06.png",
        "/assets/PNG/Retina/Blocks/block_07.png",
        "/assets/PNG/Retina/Blocks/block_08.png",
        "/assets/PNG/Retina/Crates/crate_01.png",
        "/assets/PNG/Retina/Crates/crate_02.png",
        "/assets/PNG/Retina/Crates/crate_03.png",
        "/assets/PNG/Retina/Crates/crate_04.png",
        "/assets/PNG/Retina/Crates/crate_05.png",
        "/assets/PNG/Retina/Crates/crate_06.png",
        "/assets/PNG/Retina/Crates/crate_07.png",
        "/assets/PNG/Retina/Crates/crate_08.png",
        "/assets/PNG/Retina/Crates/crate_09.png",
        "/assets/PNG/Retina/Crates/crate_10.png",
        "/assets/PNG/Retina/Crates/crate_11.png",
        "/assets/PNG/Retina/Crates/crate_12.png",
        "/assets/PNG/Retina/Crates/crate_13.png",
        "/assets/PNG/Retina/Crates/crate_14.png",
        "/assets/PNG/Retina/Crates/crate_15.png",
        "/assets/PNG/Retina/Crates/crate_16.png",
        "/assets/PNG/Retina/Crates/crate_17.png",
        "/assets/PNG/Retina/Crates/crate_18.png",
        "/assets/PNG/Retina/Crates/crate_19.png",
        "/assets/PNG/Retina/Crates/crate_20.png",
        "/assets/PNG/Retina/Crates/crate_21.png",
        "/assets/PNG/Retina/Crates/crate_22.png",
        "/assets/PNG/Retina/Crates/crate_23.png",
        "/assets/PNG/Retina/Crates/crate_24.png",
        "/assets/PNG/Retina/Crates/crate_25.png",
        "/assets/PNG/Retina/Crates/crate_26.png",
        "/assets/PNG/Retina/Crates/crate_27.png",
        "/assets/PNG/Retina/Crates/crate_28.png",
        "/assets/PNG/Retina/Crates/crate_29.png",
        "/assets/PNG/Retina/Crates/crate_30.png",
        "/assets/PNG/Retina/Crates/crate_31.png",
        "/assets/PNG/Retina/Crates/crate_32.png",
        "/assets/PNG/Retina/Crates/crate_33.png",
        "/assets/PNG/Retina/Crates/crate_34.png",
        "/assets/PNG/Retina/Crates/crate_35.png",
        "/assets/PNG/Retina/Crates/crate_36.png",
        "/assets/PNG/Retina/Crates/crate_37.png",
        "/assets/PNG/Retina/Crates/crate_38.png",
        "/assets/PNG/Retina/Crates/crate_39.png",
        "/assets/PNG/Retina/Crates/crate_40.png",
        "/assets/PNG/Retina/Crates/crate_41.png",
        "/assets/PNG/Retina/Crates/crate_42.png",
        "/assets/PNG/Retina/Crates/crate_43.png",
        "/assets/PNG/Retina/Crates/crate_44.png",
        "/assets/PNG/Retina/Crates/crate_45.png",
        "/assets/PNG/Retina/Environment/environment_01.png",
        "/assets/PNG/Retina/Environment/environment_02.png",
        "/assets/PNG/Retina/Environment/environment_03.png",
        "/assets/PNG/Retina/Environment/environment_04.png",
        "/assets/PNG/Retina/Environment/environment_05.png",
        "/assets/PNG/Retina/Environment/environment_06.png",
        "/assets/PNG/Retina/Environment/environment_07.png",
        "/assets/PNG/Retina/Environment/environment_08.png",
        "/assets/PNG/Retina/Environment/environment_09.png",
        "/assets/PNG/Retina/Environment/environment_10.png",
        "/assets/PNG/Retina/Environment/environment_11.png",
        "/assets/PNG/Retina/Environment/environment_12.png",
        "/assets/PNG/Retina/Environment/environment_13.png",
        "/assets/PNG/Retina/Environment/environment_14.png",
        "/assets/PNG/Retina/Environment/environment_15.png",
        "/assets/PNG/Retina/Environment/environment_16.png",
        "/assets/PNG/Retina/Ground/ground_01.png",
        "/assets/PNG/Retina/Ground/ground_02.png",
        "/assets/PNG/Retina/Ground/ground_03.png",
        "/assets/PNG/Retina/Ground/ground_04.png",
        "/assets/PNG/Retina/Ground/ground_05.png",
        "/assets/PNG/Retina/Ground/ground_06.png",
        "/assets/PNG/Retina/Player/player_01.png",
        "/assets/PNG/Retina/Player/player_02.png",
        "/assets/PNG/Retina/Player/player_03.png",
        "/assets/PNG/Retina/Player/player_04.png",
        "/assets/PNG/Retina/Player/player_05.png",
        "/assets/PNG/Retina/Player/player_06.png",
        "/assets/PNG/Retina/Player/player_07.png",
        "/assets/PNG/Retina/Player/player_08.png",
        "/assets/PNG/Retina/Player/player_09.png",
        "/assets/PNG/Retina/Player/player_10.png",
        "/assets/PNG/Retina/Player/player_11.png",
        "/assets/PNG/Retina/Player/player_12.png",
        "/assets/PNG/Retina/Player/player_13.png",
        "/assets/PNG/Retina/Player/player_14.png",
        "/assets/PNG/Retina/Player/player_15.png",
        "/assets/PNG/Retina/Player/player_16.png",
        "/assets/PNG/Retina/Player/player_17.png",
        "/assets/PNG/Retina/Player/player_18.png",
        "/assets/PNG/Retina/Player/player_19.png",
        "/assets/PNG/Retina/Player/player_20.png",
        "/assets/PNG/Retina/Player/player_21.png",
        "/assets/PNG/Retina/Player/player_22.png",
        "/assets/PNG/Retina/Player/player_23.png",
        "/assets/PNG/Retina/Player/player_24.png",
        "/assets/PNG/Retina/playerFace.png",
        "/assets/PNG/Retina/playerFace_dark.png",
        "/assets/PNG/Retina/ret_74.png",
        "/assets/PNG/back.png",
        "/assets/PNG/background.png",
        "/assets/PNG/cross.png",
        "/assets/PNG/culture.png",
        "/assets/PNG/education.png",
        "/assets/PNG/food.png",
        "/assets/PNG/health.png",
        "/assets/PNG/job.png",
        "/assets/PNG/lock.png",
        "/assets/PNG/nadgryzione ciasteczko.png",
        "/assets/PNG/nature.png",
        "/assets/PNG/people.png",
        "/assets/PNG/place of living.png",
        "/assets/PNG/podgląd całości.png",
        "/assets/PNG/private life.png",
        "/assets/PNG/reset.png",
        "/assets/PNG/shopping.png",
        "/assets/PNG/sport.png",
        "/assets/PNG/state and society.png",
        "/assets/PNG/technology.png",
        "/assets/PNG/tick.png",
        "/assets/PNG/tort.png",
        "/assets/PNG/travelling.png",
        "/assets/fonts/Derivia-Regular.otf",
        "/assets/fonts/lazy_dog.ttf",
        "/assets/icons/icon-128x128.png",
        "/assets/icons/icon-144x144.png",
        "/assets/icons/icon-152x152.png",
        "/assets/icons/icon-192x192.png",
        "/assets/icons/icon-384x384.png",
        "/assets/icons/icon-512x512.png",
        "/assets/icons/icon-72x72.png",
        "/assets/icons/icon-96x96.png",
        "/background.7d809664eb2af1cf.png",
        "/lazy_dog.381a7961f1999aa8.ttf"
      ],
      "patterns": []
    }
  ],
  "dataGroups": [],
  "hashTable": {
    "/Derivia-Regular.c8b8089c6db01ce3.otf": "caaf5f38bd520dc78dbb1194eaf117a46403cb50",
    "/assets/PNG/Default size/Blocks/block_01.png": "73a8ccb6b3b58ff9a89559a86693c399033c34d8",
    "/assets/PNG/Default size/Blocks/block_02.png": "a844499fff50b653cde07cbdddbf23e049de073b",
    "/assets/PNG/Default size/Blocks/block_03.png": "0a0ead144c5a7430fee56c10e382250d484925e3",
    "/assets/PNG/Default size/Blocks/block_04.png": "545dceceaa0b2fb01c9b40b2418f3d2e3997291b",
    "/assets/PNG/Default size/Blocks/block_05.png": "6bd02adf08f8579a100932173935e09a7b1b52f7",
    "/assets/PNG/Default size/Blocks/block_06.png": "9707b1db9d38f5052388fa76ba12e2da2bc0d6a5",
    "/assets/PNG/Default size/Blocks/block_07.png": "c6a49a2424ca5ed5d169fa42837c33302d2cb8e5",
    "/assets/PNG/Default size/Blocks/block_08.png": "b41da24a78ff9396c9860bea4962493d4057ff90",
    "/assets/PNG/Default size/Crates/crate_01.png": "d5f343fbb011fc2f75195c84996bd8891a34d801",
    "/assets/PNG/Default size/Crates/crate_02.png": "3688aad934e52a628b9e87f4154792bc3c7d3d1a",
    "/assets/PNG/Default size/Crates/crate_03.png": "9fd06eda286ad3040b426513dd788fefe4ac6c39",
    "/assets/PNG/Default size/Crates/crate_04.png": "bf5bbda21cfe77bb0c13f93e1b83829f5d5177a6",
    "/assets/PNG/Default size/Crates/crate_05.png": "a6e6d3b9b8e743b742dab92c84abbdbce0fda10f",
    "/assets/PNG/Default size/Crates/crate_06.png": "6f98d537e4fac5e56d8e6196984e11469b600211",
    "/assets/PNG/Default size/Crates/crate_07.png": "68e36e14266e4b45b57971ee3fee51b8c857ad35",
    "/assets/PNG/Default size/Crates/crate_08.png": "68dfebfd1a9b9d6089b6282397efb55c20746d97",
    "/assets/PNG/Default size/Crates/crate_09.png": "e54f69671afed95e0c8a03b174207a800a5911c4",
    "/assets/PNG/Default size/Crates/crate_10.png": "3da964070bc199c60b35637b67bd194b92a24b8f",
    "/assets/PNG/Default size/Crates/crate_11.png": "b87aa0316c122b96f272f2383c97ceb0bf815338",
    "/assets/PNG/Default size/Crates/crate_12.png": "ba2209d99013e5cfa838d6fcd3e6bc2145546584",
    "/assets/PNG/Default size/Crates/crate_13.png": "260b2e93d18fe03847c1bd427635b3d99acf1c17",
    "/assets/PNG/Default size/Crates/crate_14.png": "697a2f852a5d1435c9e0bc55f96304a8f336075f",
    "/assets/PNG/Default size/Crates/crate_15.png": "44aefb4cbc70da9e91d2ba1e453993033e6dbb22",
    "/assets/PNG/Default size/Crates/crate_16.png": "ac03ff1b16cb3e86082a635a8239b9ca16ed1f3e",
    "/assets/PNG/Default size/Crates/crate_17.png": "295e04bf452aa213022146cb8d65e9d35b4367bc",
    "/assets/PNG/Default size/Crates/crate_18.png": "8aa7ab624f466616d588ce7e0da971dea104ff6b",
    "/assets/PNG/Default size/Crates/crate_19.png": "3ce6dc1a9ae0278ceec04f0f2f265569dc163b81",
    "/assets/PNG/Default size/Crates/crate_20.png": "f7a40fb77375e14df5e7fff5db25d63a5f0e54d0",
    "/assets/PNG/Default size/Crates/crate_21.png": "e4a5224e6765f1e2c7c6597f25823191f88bb7d4",
    "/assets/PNG/Default size/Crates/crate_22.png": "0c0f38d74657abe5ae12f190cba6c2d09b60dc9a",
    "/assets/PNG/Default size/Crates/crate_23.png": "185de3c0c2588526b934f87eee1e1ec8137003d2",
    "/assets/PNG/Default size/Crates/crate_24.png": "94ba97e34a48c4f8d8daf845525052ce39f89c5a",
    "/assets/PNG/Default size/Crates/crate_25.png": "f15ca9258b9dd3314d8747c2e55bcfe1304d5926",
    "/assets/PNG/Default size/Crates/crate_26.png": "e99bc5a48c9a83c070a8c3fe2d97fab5f380f6ad",
    "/assets/PNG/Default size/Crates/crate_27.png": "55f1976810e6816379e825c6cda051aaff8a393d",
    "/assets/PNG/Default size/Crates/crate_28.png": "e47a53079f6b0068f27fafb50507b9ebc209df0d",
    "/assets/PNG/Default size/Crates/crate_29.png": "6aa5ce00d5962b23d9a1b6cdf58e68aed763a48a",
    "/assets/PNG/Default size/Crates/crate_30.png": "469af74768c142e46eb9aa2442bdb456c865d6c0",
    "/assets/PNG/Default size/Crates/crate_31.png": "1b6fb9e5177cb387e4bc51b214aa2f1f59502c8b",
    "/assets/PNG/Default size/Crates/crate_32.png": "f7693261495b4af773d1dd86d11be786e06d5a19",
    "/assets/PNG/Default size/Crates/crate_33.png": "78d8331bad5899f3a7ec3f7f2b113fe32448bbd7",
    "/assets/PNG/Default size/Crates/crate_34.png": "b00d4d42f500bd40884ee2afc1a2499c28a6dfdc",
    "/assets/PNG/Default size/Crates/crate_35.png": "36da4d6e4b51bf39cf30bec2b18610f91bcbdd29",
    "/assets/PNG/Default size/Crates/crate_36.png": "6e13ffbe402586441d27ffcf300524737cb9dd78",
    "/assets/PNG/Default size/Crates/crate_37.png": "944eecfd9c8f7282ce0d8cdf6c6f60709bb633c5",
    "/assets/PNG/Default size/Crates/crate_38.png": "70da32a363303c1dfe2384d29deb79546a9c8340",
    "/assets/PNG/Default size/Crates/crate_39.png": "03d22861a4fad453f69b1848e4e7f043ecdc6a5d",
    "/assets/PNG/Default size/Crates/crate_40.png": "5acce5d5c12aa6adbb3bfa022f5e45eae94e2a9b",
    "/assets/PNG/Default size/Crates/crate_41.png": "c7808a40d70ea524ccb80bd850927a91622bea72",
    "/assets/PNG/Default size/Crates/crate_42.png": "d76d39e3dfc08800363b33c6ef285762a1f0a099",
    "/assets/PNG/Default size/Crates/crate_43.png": "022b02d16d522fc5a6d5dd42863e557ea82c780f",
    "/assets/PNG/Default size/Crates/crate_44.png": "b42cf39667a1db27a75958bac5f3f6634dfd4980",
    "/assets/PNG/Default size/Crates/crate_45.png": "1ecc5ddcbac6340bff041591d027b960c0a78808",
    "/assets/PNG/Default size/Environment/environment_01.png": "66171cb11ff15f99af826f7039ff5ea32df70548",
    "/assets/PNG/Default size/Environment/environment_02.png": "1ecdd3517391a4119c9a621d847f416c521c0911",
    "/assets/PNG/Default size/Environment/environment_03.png": "260f6f12480f6dfce178c70f6288b2088384a5b7",
    "/assets/PNG/Default size/Environment/environment_04.png": "dec9386b71378a325376e54a5ec07a594a4ccf5d",
    "/assets/PNG/Default size/Environment/environment_05.png": "8b81744869f291fef929e25b40204eaa4cfea3ed",
    "/assets/PNG/Default size/Environment/environment_06.png": "9ab428db8cd382810d3a4730eadd5bae68ae548c",
    "/assets/PNG/Default size/Environment/environment_07.png": "eedabfa9be6c7f6db5dc20f4c99464f20ec1d304",
    "/assets/PNG/Default size/Environment/environment_08.png": "03b80582e16c4b8078d1a3cecb75c670ac8d1b72",
    "/assets/PNG/Default size/Environment/environment_09.png": "a47668097a4c416206a03732f37fd0484b8a56ac",
    "/assets/PNG/Default size/Environment/environment_10.png": "6f98d26b3b3139b2a91e85ceca3324f977caa369",
    "/assets/PNG/Default size/Environment/environment_11.png": "c4bf5c2f5833c8aaa45b957bd3e4fa9bb8cca4d1",
    "/assets/PNG/Default size/Environment/environment_12.png": "fb864e9f634f1c5da99a19e691b3dd76cafd94ce",
    "/assets/PNG/Default size/Environment/environment_13.png": "8c2c8f6a2242f2172a43ad05b14e426b5adde8dd",
    "/assets/PNG/Default size/Environment/environment_14.png": "a29f27e7acf6753927fb7cb0be083ed33160eec1",
    "/assets/PNG/Default size/Environment/environment_15.png": "7b3c97288e2f7865fc13abed6bd65e42f33fe5e9",
    "/assets/PNG/Default size/Environment/environment_16.png": "e1a08183872182bab3ebd23b9b3b1be1b82d1bb6",
    "/assets/PNG/Default size/Ground/ground_01.png": "2e4edab7b9594aa9e6725d1c4da2bcceea7d11c0",
    "/assets/PNG/Default size/Ground/ground_02.png": "73eb94a44a0c6f37172945960aacea31649874c9",
    "/assets/PNG/Default size/Ground/ground_03.png": "593598ebbb06e56ac87fecff9fd6aad6243b70a3",
    "/assets/PNG/Default size/Ground/ground_04.png": "663b059d3e3fbf65354d1da40f0d351c9b706e51",
    "/assets/PNG/Default size/Ground/ground_05.png": "f7c3e17e5975741f04cbb013c52284afe4848cee",
    "/assets/PNG/Default size/Ground/ground_06.png": "047ca6fe80f7cddfe097ff89031bcebb4969cbd0",
    "/assets/PNG/Default size/Player/player_01.png": "7eccd6f63433b9518ab68168a299b9f965baf670",
    "/assets/PNG/Default size/Player/player_02.png": "3967c8636c7a1e782c8acac4fa4e693e00bdbcf2",
    "/assets/PNG/Default size/Player/player_03.png": "ac829afdf617a4895fc31dd18eaadddbebdd0ca0",
    "/assets/PNG/Default size/Player/player_04.png": "7302ddbad5874b253e1978cf89070aa9aaffc11b",
    "/assets/PNG/Default size/Player/player_05.png": "e3211e89dd1afad1bd9d3281ea846e8d413fde82",
    "/assets/PNG/Default size/Player/player_06.png": "46a774a86edf0362c81742db536c5583d216331f",
    "/assets/PNG/Default size/Player/player_07.png": "b57f6d75b2a1d6ba27be729008140fd73e68583d",
    "/assets/PNG/Default size/Player/player_08.png": "1d493740a5967a6d74ab1ad7f8e7dcfddcad536c",
    "/assets/PNG/Default size/Player/player_09.png": "0881abd4d61360e9005d22c5d49ab9f5ac71ba93",
    "/assets/PNG/Default size/Player/player_10.png": "5cf1159cde734d8d61dcc573f10b5ddf6d0b8e89",
    "/assets/PNG/Default size/Player/player_11.png": "de37a798508c2cbac71044a7b62141b7f8aa8821",
    "/assets/PNG/Default size/Player/player_12.png": "ebbc6059e5a65bd40c29fab719c72b24aa694220",
    "/assets/PNG/Default size/Player/player_13.png": "729ccbadd717943d075d1bc6a4fe5a0856885d9d",
    "/assets/PNG/Default size/Player/player_14.png": "c110ba03af0dd218b89e42176c5dc21f7ee627ed",
    "/assets/PNG/Default size/Player/player_15.png": "80903f7c3dce22f775cf1277cf832ad93d02a4ea",
    "/assets/PNG/Default size/Player/player_16.png": "9865096ca651808222f7000194aec41db6b5124a",
    "/assets/PNG/Default size/Player/player_17.png": "a7a8dcdabeea6cfb8508d43b7395e41dfc48fde3",
    "/assets/PNG/Default size/Player/player_18.png": "a70f97010df1fd85afe333e62833f90518de9f4a",
    "/assets/PNG/Default size/Player/player_19.png": "58c9467dc53ca1886ec2cc96459c66a15583fa5f",
    "/assets/PNG/Default size/Player/player_20.png": "0a8b9a588467acc06543f3e838863ea56a1910c4",
    "/assets/PNG/Default size/Player/player_21.png": "f5ec333f8e1492d4513489f784b89d5c07069d07",
    "/assets/PNG/Default size/Player/player_22.png": "6a2fd094c13bc12f188e8fe1b13c95c9747caea0",
    "/assets/PNG/Default size/Player/player_23.png": "c604b4ac9ffeaea279cabe8b2975d3bbf7773ec1",
    "/assets/PNG/Default size/Player/player_24.png": "0ab48e3b0bf046d13789b47a26cb5f2bb1789667",
    "/assets/PNG/Default size/playerFace.png": "acdfdcb4acf575dc6b1e46a3698878f09d4f39bc",
    "/assets/PNG/Default size/playerFace_dark.png": "0489044b4c8360731b951af7313da91dffdb96e7",
    "/assets/PNG/Default size/playerFace_outline.png": "9a68da44d6ffe01905a46cebb9258fc52fcb5b5f",
    "/assets/PNG/Retina/Blocks/block_01.png": "9535aaadb0e544efd1ef2471ade3b8fb3eedbbef",
    "/assets/PNG/Retina/Blocks/block_02.png": "71a7717bca85f68fdbc94cc334bbff9ec97ee054",
    "/assets/PNG/Retina/Blocks/block_03.png": "0114622e0207d8884c7b8000d3a0d6740d2470d3",
    "/assets/PNG/Retina/Blocks/block_04.png": "586856b1caa792e9b3e1d8b31647abb99550b46a",
    "/assets/PNG/Retina/Blocks/block_05.png": "0d85341222639f876f3cb9c0b723090de1271d87",
    "/assets/PNG/Retina/Blocks/block_06.png": "9e75c7a684b302f48daf237c698b71d0901d253d",
    "/assets/PNG/Retina/Blocks/block_07.png": "92f508cf08bc3aa4f735d88804fb25e24a0463b6",
    "/assets/PNG/Retina/Blocks/block_08.png": "07605914cddde39da8c073ec233644b046292a6b",
    "/assets/PNG/Retina/Crates/crate_01.png": "08144b99d99bb9296a71a1d2bfb49121f4c40bfd",
    "/assets/PNG/Retina/Crates/crate_02.png": "acca0fb66b8ed6b2e77c76a1bcf5aa195ff19f7a",
    "/assets/PNG/Retina/Crates/crate_03.png": "ef8a1fb7de4230e94549b73fa4632f59fe8f1813",
    "/assets/PNG/Retina/Crates/crate_04.png": "a555366cb3533b43a9ccfd4aeba594de7a98362d",
    "/assets/PNG/Retina/Crates/crate_05.png": "7571bab5cf334ab3e260ffeda24b21cac21fca51",
    "/assets/PNG/Retina/Crates/crate_06.png": "fedb3b1ec16f1609432defd95a892af1dcca654d",
    "/assets/PNG/Retina/Crates/crate_07.png": "0c21135db3c7b7c3d047c1eb66d4b141bf0e5bbb",
    "/assets/PNG/Retina/Crates/crate_08.png": "c467627b954421dc9dfdc8b361ffdb82744e9b99",
    "/assets/PNG/Retina/Crates/crate_09.png": "b0ae524b1879f1a5e936644f79aae690f9fc34f0",
    "/assets/PNG/Retina/Crates/crate_10.png": "d9fbb9f445ad65162e6af58d4980b97ac0b085e2",
    "/assets/PNG/Retina/Crates/crate_11.png": "4032ebb4e5d04cc2b62ed494cac61ab455e15911",
    "/assets/PNG/Retina/Crates/crate_12.png": "d1d739c142218b3c7ae81082abade3ef60dc2404",
    "/assets/PNG/Retina/Crates/crate_13.png": "df91963ad40c75c27dc6b743861482e5b1225a09",
    "/assets/PNG/Retina/Crates/crate_14.png": "9f838ec520ea6b791e16c5fd9bedd8c6ba7ce498",
    "/assets/PNG/Retina/Crates/crate_15.png": "0f3861eadb087bae5fec3086ea13371765407786",
    "/assets/PNG/Retina/Crates/crate_16.png": "4143c316b97b18fe59d4bbbfbfad8979f0017132",
    "/assets/PNG/Retina/Crates/crate_17.png": "07dcf5c4173a3b2ac71b1a0c6693bc491629a6ea",
    "/assets/PNG/Retina/Crates/crate_18.png": "4170b0ade2877b6ddc51202f9f49b47340ae6578",
    "/assets/PNG/Retina/Crates/crate_19.png": "64af5cddd2b70a7785169483d4faace933cc8d04",
    "/assets/PNG/Retina/Crates/crate_20.png": "661abcb2a620e5ecd961558e8863563a3d688164",
    "/assets/PNG/Retina/Crates/crate_21.png": "ec8b2eb17bf0f16361c7765b12c420d8740ba86b",
    "/assets/PNG/Retina/Crates/crate_22.png": "bca48e19810106b0b7a236284fccbd2585dc835f",
    "/assets/PNG/Retina/Crates/crate_23.png": "911fa7eaa8bf37d30767a10c20bee04b150c8d64",
    "/assets/PNG/Retina/Crates/crate_24.png": "d5786e9287de70c21a764f01ac9a8779a46fb7b0",
    "/assets/PNG/Retina/Crates/crate_25.png": "332487a554b4916300a1bce6044864aed1737b3a",
    "/assets/PNG/Retina/Crates/crate_26.png": "dab268d5c1db4b124f7290f27de91cae564b70df",
    "/assets/PNG/Retina/Crates/crate_27.png": "7cd477e48adf02f63a7ce92c4863094e60a2963b",
    "/assets/PNG/Retina/Crates/crate_28.png": "45a28966d5ca4d4396ed5cab660c490d4429b9cf",
    "/assets/PNG/Retina/Crates/crate_29.png": "3cd8e2ebcac396d179ee2fa4089ba74ca1464425",
    "/assets/PNG/Retina/Crates/crate_30.png": "961c13df5b21d88125aae81b5b3c8a8b04fa5ff0",
    "/assets/PNG/Retina/Crates/crate_31.png": "391250ec4687ee26a55ffeabac43ac2fc3561330",
    "/assets/PNG/Retina/Crates/crate_32.png": "ac411e5f210337b993e66426f0394a0dd64d9bc4",
    "/assets/PNG/Retina/Crates/crate_33.png": "885b5cdd9fd607e30625cf4624c300f645220abe",
    "/assets/PNG/Retina/Crates/crate_34.png": "68da1dc242d9e0aa87ee09ceebb6a166c87a1133",
    "/assets/PNG/Retina/Crates/crate_35.png": "7d950d2d5d90bfcb7e0e291defd5f36cf0af241d",
    "/assets/PNG/Retina/Crates/crate_36.png": "e9a0630c3fcccb784f0baddb1c2af386f838d5eb",
    "/assets/PNG/Retina/Crates/crate_37.png": "62a9011323b0d1f15662360be508ab1c1df001e7",
    "/assets/PNG/Retina/Crates/crate_38.png": "d056699a35f2184196498d97ef9ec6cd76e31b6b",
    "/assets/PNG/Retina/Crates/crate_39.png": "2bedfd5e0a758e6d8e169ac700b352f248de41d7",
    "/assets/PNG/Retina/Crates/crate_40.png": "c39ae99ff7b64aefeedbfe32cbe5cb2969aff3d5",
    "/assets/PNG/Retina/Crates/crate_41.png": "f557322289bb309c099d29bad6de1628b87fd114",
    "/assets/PNG/Retina/Crates/crate_42.png": "bbb8a0fbbb2dd2b5c9bf04637d6d1bf548eac15b",
    "/assets/PNG/Retina/Crates/crate_43.png": "5824c8935e40c6199e259d2abab8f78ceea31304",
    "/assets/PNG/Retina/Crates/crate_44.png": "86833bfcbd53175882d9c75dcbd14fc7b97bc1ba",
    "/assets/PNG/Retina/Crates/crate_45.png": "ddf42f1bcb3c1b672f4ae2d5726b2bdf6a07e983",
    "/assets/PNG/Retina/Environment/environment_01.png": "afcb23632548b77a58bc57c803f8f3f902d89b15",
    "/assets/PNG/Retina/Environment/environment_02.png": "86763526bb59a2ac2548293b5ddb608bc54d7fba",
    "/assets/PNG/Retina/Environment/environment_03.png": "7542ef695932da29a9cbd0993e6cc4d6a4b197ce",
    "/assets/PNG/Retina/Environment/environment_04.png": "d0e3a512f69d442267adb08d46307501984e98f9",
    "/assets/PNG/Retina/Environment/environment_05.png": "a137a17b4e1569f878c16213a078dc115a3763ec",
    "/assets/PNG/Retina/Environment/environment_06.png": "6faa07c3f4384d1c2c69b06548c2a3d576ddebb1",
    "/assets/PNG/Retina/Environment/environment_07.png": "79fdc1df6069a7333669a5662f7c859c95e1aae8",
    "/assets/PNG/Retina/Environment/environment_08.png": "753b082ea512506a7f721a0287c58fb4cce9bfb6",
    "/assets/PNG/Retina/Environment/environment_09.png": "4174beae330587d940606f9af6aa5c21bcf750ac",
    "/assets/PNG/Retina/Environment/environment_10.png": "548f85477a0b1081409620a89f94788e30f6f12c",
    "/assets/PNG/Retina/Environment/environment_11.png": "24c8ab91d66d5d09cfda7c4ec748b426fc4068f0",
    "/assets/PNG/Retina/Environment/environment_12.png": "bf17a3c203a4647390ddb23ccee16f6df78d50b5",
    "/assets/PNG/Retina/Environment/environment_13.png": "898ea8c3ec94c6ea9891ca5b2b47d53ba02272ab",
    "/assets/PNG/Retina/Environment/environment_14.png": "799d54a0dfaec0ac302d11797d19d9e1cdb7e49c",
    "/assets/PNG/Retina/Environment/environment_15.png": "0f4c68b643f5f72e67ac2fd9ce4e77d6763468f2",
    "/assets/PNG/Retina/Environment/environment_16.png": "1ac5633253d56ebdf640f808c285ca83b6f1c0a8",
    "/assets/PNG/Retina/Ground/ground_01.png": "4690c07df92b6d1faede2890b05dcacdb222bc42",
    "/assets/PNG/Retina/Ground/ground_02.png": "14bdafd84e1894b39536ff489028b9e24b22807c",
    "/assets/PNG/Retina/Ground/ground_03.png": "77107acff795f2c8b2f55fb3562d9a4400d6ad5c",
    "/assets/PNG/Retina/Ground/ground_04.png": "c7f1cca8c94151373d4a18e70c280e60772d27cb",
    "/assets/PNG/Retina/Ground/ground_05.png": "38a1e5b0671d1489356c1f764b0eb623edcff944",
    "/assets/PNG/Retina/Ground/ground_06.png": "1f329486b21068a0db0504d374d4fff0dd4f65df",
    "/assets/PNG/Retina/Player/player_01.png": "30fecfc02a2753e73c62dcf31003dc9777b2dc69",
    "/assets/PNG/Retina/Player/player_02.png": "d4221edb08174e838be6e35352550b8211cbf525",
    "/assets/PNG/Retina/Player/player_03.png": "826f3dad7ef4ffa7a0da8a7bc22914efba8bb848",
    "/assets/PNG/Retina/Player/player_04.png": "7ea6e33691efae4d74e92073e748f1f123b350ee",
    "/assets/PNG/Retina/Player/player_05.png": "28ee8532f74ca31f3504781c1c8df056d86ca378",
    "/assets/PNG/Retina/Player/player_06.png": "c1e6e6c9c4dd3fc47f1f017ad0532b9e5b688481",
    "/assets/PNG/Retina/Player/player_07.png": "a1a421b8985b1329a6aef6efb04ceaf84a107a75",
    "/assets/PNG/Retina/Player/player_08.png": "ad89b9d3a46a65eed13e7e708c7d6bad2b12e911",
    "/assets/PNG/Retina/Player/player_09.png": "33f4ab514b4f699881bf872194b453ea1a0e6552",
    "/assets/PNG/Retina/Player/player_10.png": "581868e77b7289acc522f4edbcfe8fb26f872dd0",
    "/assets/PNG/Retina/Player/player_11.png": "7a46c15de4bfd3568aae6bb4dd3fa01138ae4e3d",
    "/assets/PNG/Retina/Player/player_12.png": "1ecc54e393b222a5f96d398a149d60393ed6b125",
    "/assets/PNG/Retina/Player/player_13.png": "7e276c0939270f63ab7f0717da56440562d92657",
    "/assets/PNG/Retina/Player/player_14.png": "07b51f4c89f161f9af506b78175d8185837bf2fc",
    "/assets/PNG/Retina/Player/player_15.png": "23085318f0e57ee3859dd3d432b1e846a5a7ba8a",
    "/assets/PNG/Retina/Player/player_16.png": "a87186df10a9533ebe3bd55f24c9f6a70602f69d",
    "/assets/PNG/Retina/Player/player_17.png": "a4bb8b136cde9152044d8ec2af8e5c7d29040d85",
    "/assets/PNG/Retina/Player/player_18.png": "ac24a6e1793514124da3061a7be567ff9604f8e4",
    "/assets/PNG/Retina/Player/player_19.png": "c535f8ee91bca4ec05a223cfe966d013199975a8",
    "/assets/PNG/Retina/Player/player_20.png": "1ecadf59f0ef53026446fa304256c177238fb81f",
    "/assets/PNG/Retina/Player/player_21.png": "8611e808fff08f711640bc8717638de6f9f99519",
    "/assets/PNG/Retina/Player/player_22.png": "a4780f8ef05704010af834caeeb8f894c4f716cc",
    "/assets/PNG/Retina/Player/player_23.png": "3b3babcf17908ec091aa39d933d48e33bce7eeda",
    "/assets/PNG/Retina/Player/player_24.png": "9f45bf9dd7f94f927f3d3778fd799916579d313e",
    "/assets/PNG/Retina/playerFace.png": "c8b36500d67c3f4d2d56cac13c1d4cd14b6e1346",
    "/assets/PNG/Retina/playerFace_dark.png": "ced73bbbb59e8c27ad45b874ce85b904675fa448",
    "/assets/PNG/Retina/ret_74.png": "a3405038bb6ecc030c6d5ec00d666f77edc60dfa",
    "/assets/PNG/back.png": "08d61552bc0ec402530888a9560be7846efe502d",
    "/assets/PNG/background.png": "50341023ccb56ebfd03a28a43e4b8673f5d60e5e",
    "/assets/PNG/cross.png": "b1499c4b2a42f3cce52900b4c0fd65197dca9413",
    "/assets/PNG/culture.png": "44ddb2f5c46a97e473ba3f64759659bb52427986",
    "/assets/PNG/education.png": "785363e49573d6b482725fcdb3d5a89c8fb9a4d2",
    "/assets/PNG/food.png": "6d6557d1f9c0c5dcd8f0c5b9468437f0d07e99ee",
    "/assets/PNG/health.png": "4b2a34a05ece54565c940e6d5b62dc7ee75dba00",
    "/assets/PNG/job.png": "c8382afee71c58a73aac26b4042465afe36e673f",
    "/assets/PNG/lock.png": "4f89a1dee622839a53a6d39a017d3409a8c44917",
    "/assets/PNG/nadgryzione ciasteczko.png": "febe27ba9c30444bc6efc611940c7814ddb86495",
    "/assets/PNG/nature.png": "3747616e2f621a3f2d09cf8008181999591f95b7",
    "/assets/PNG/people.png": "a5c74b6e8c6b65b2d8b3995e566dfd04f512a5df",
    "/assets/PNG/place of living.png": "ea18f84d4c851a36ac3e266e5d2de24918b971e5",
    "/assets/PNG/podgląd całości.png": "55cccf03ae7dec4a9dd536ec902f72c832626e70",
    "/assets/PNG/private life.png": "4e0539eba2523d7adfc79126f127458df0b53322",
    "/assets/PNG/reset.png": "b251e018dbaa3b48702400dff8f4b337e8db46d2",
    "/assets/PNG/shopping.png": "2076ef95dfea999e0def3b926f9af2bb79e93b05",
    "/assets/PNG/sport.png": "5e8b1388a182f458ddda57912bdb661158f3f584",
    "/assets/PNG/state and society.png": "bfcc91fb8f539700d093f521129375d95fd8172c",
    "/assets/PNG/technology.png": "a730e363fd08734c37a673c2a812828c98e1b138",
    "/assets/PNG/tick.png": "f64216c95de16eb8aa309a75c48463ba895e695d",
    "/assets/PNG/tort.png": "141eb9bef518de482d2921eba1b03fac3b7a1f94",
    "/assets/PNG/travelling.png": "c04e9de003eeded9ed474e44081a6d72ec5e8ce2",
    "/assets/fonts/Derivia-Regular.otf": "caaf5f38bd520dc78dbb1194eaf117a46403cb50",
    "/assets/fonts/lazy_dog.ttf": "04d5577a44562ac0ce974532b5327c625f2aa04e",
    "/assets/icons/icon-128x128.png": "dae3b6ed49bdaf4327b92531d4b5b4a5d30c7532",
    "/assets/icons/icon-144x144.png": "b0bd89982e08f9bd2b642928f5391915b74799a7",
    "/assets/icons/icon-152x152.png": "7479a9477815dfd9668d60f8b3b2fba709b91310",
    "/assets/icons/icon-192x192.png": "1abd80d431a237a853ce38147d8c63752f10933b",
    "/assets/icons/icon-384x384.png": "329749cd6393768d3131ed6304c136b1ca05f2fd",
    "/assets/icons/icon-512x512.png": "559d9c4318b45a1f2b10596bbb4c960fe521dbcc",
    "/assets/icons/icon-72x72.png": "c457e56089a36952cd67156f9996bc4ce54a5ed9",
    "/assets/icons/icon-96x96.png": "3914125a4b445bf111c5627875fc190f560daa41",
    "/background.7d809664eb2af1cf.png": "50341023ccb56ebfd03a28a43e4b8673f5d60e5e",
    "/favicon.ico": "22f6a4a3bcaafafb0254e0f2fa4ceb89e505e8b2",
    "/index.html": "fb6f390847ce3f633f6e51ffefff45ad707bd5a0",
    "/lazy_dog.381a7961f1999aa8.ttf": "04d5577a44562ac0ce974532b5327c625f2aa04e",
    "/main.29abf87b953e0e6f.js": "d6607dbb72b01f26b85e63ae17bbc86a419c9e83",
    "/manifest.webmanifest": "cba5ed5e21dfc457be53cfe66f619d44d5a7457c",
    "/polyfills.03cfe1edbec1212d.js": "5e2bc0e35aec5d57b34d7f29553d11104ad30cec",
    "/runtime.e7648955bf48ba73.js": "27fab0f4c08ad4f52f1eb30781617108caf621bd",
    "/styles.a914d5a691cddd4b.css": "c350f458f08ce66fd76cfee70deafb56113b75be"
  },
  "navigationUrls": [
    {
      "positive": true,
      "regex": "^\\/.*$"
    },
    {
      "positive": false,
      "regex": "^\\/(?:.+\\/)?[^/]*\\.[^/]*$"
    },
    {
      "positive": false,
      "regex": "^\\/(?:.+\\/)?[^/]*__[^/]*$"
    },
    {
      "positive": false,
      "regex": "^\\/(?:.+\\/)?[^/]*__[^/]*\\/.*$"
    }
  ],
  "navigationRequestStrategy": "performance"
}